db_sync_tool/__init__.py
db_sync_tool/__main__.py
db_sync_tool/cli.py
db_sync_tool/info.py
db_sync_tool/sync.py
db_sync_tool/database/__init__.py
db_sync_tool/database/process.py
db_sync_tool/database/utility.py
db_sync_tool/recipes/__init__.py
db_sync_tool/recipes/drupal.py
db_sync_tool/recipes/laravel.py
db_sync_tool/recipes/parsing.py
db_sync_tool/recipes/symfony.py
db_sync_tool/recipes/typo3.py
db_sync_tool/recipes/wordpress.py
db_sync_tool/remote/__init__.py
db_sync_tool/remote/client.py
db_sync_tool/remote/file_transfer.py
db_sync_tool/remote/rsync.py
db_sync_tool/remote/system.py
db_sync_tool/remote/transfer.py
db_sync_tool/remote/utility.py
db_sync_tool/utility/__init__.py
db_sync_tool/utility/config.py
db_sync_tool/utility/config_resolver.py
db_sync_tool/utility/console.py
db_sync_tool/utility/exceptions.py
db_sync_tool/utility/helper.py
db_sync_tool/utility/info.py
db_sync_tool/utility/log.py
db_sync_tool/utility/logging_config.py
db_sync_tool/utility/mode.py
db_sync_tool/utility/output.py
db_sync_tool/utility/parser.py
db_sync_tool/utility/pure.py
db_sync_tool/utility/security.py
db_sync_tool/utility/system.py
db_sync_tool/utility/validation.py
db_sync_tool_kmi-3.0.3.dist-info/licenses/LICENSE
db_sync_tool_kmi-3.0.3.dist-info/METADATA
db_sync_tool_kmi-3.0.3.dist-info/WHEEL
db_sync_tool_kmi-3.0.3.dist-info/entry_points.txt
db_sync_tool_kmi-3.0.3.dist-info/top_level.txt
db_sync_tool_kmi-3.0.3.dist-info/RECORD
