Metadata-Version: 2.4
Name: db_sync_tool-kmi
Version: 3.0.3
Summary: Synchronize a database from and to host systems.
Home-page: https://github.com/jackd248/db-sync-tool
Author: Konrad Michalik
Author-email: support@konradmichalik.eu
License: MIT
Classifier: Programming Language :: Python :: 3.10
Classifier: Programming Language :: Python :: 3.11
Classifier: Programming Language :: Python :: 3.12
Classifier: Programming Language :: Python :: 3.13
Classifier: Programming Language :: Python :: 3.14
Classifier: Development Status :: 5 - Production/Stable
Classifier: License :: OSI Approved :: MIT License
Classifier: Operating System :: MacOS :: MacOS X
Classifier: Operating System :: Microsoft :: Windows
Classifier: Operating System :: POSIX
Classifier: Topic :: Database
Classifier: Intended Audience :: Developers
Requires-Python: >=3.10
License-File: LICENSE
Requires-Dist: paramiko>=4.0
Requires-Dist: pyyaml>=6.0.2
Requires-Dist: jsonschema>=4.20
Requires-Dist: requests>=2.31.0
Requires-Dist: semantic_version>=2.10.0
Requires-Dist: rich>=13.0
Requires-Dist: typer[all]>=0.15.0
Dynamic: author
Dynamic: author-email
Dynamic: classifier
Dynamic: description
Dynamic: description-content-type
Dynamic: home-page
Dynamic: license
Dynamic: license-file
Dynamic: requires-dist
Dynamic: requires-python
Dynamic: summary
